{
  "info": {
    "description": "data",
    "version": "1.0",
    "year": 2025,
    "contributor": "search engine",
    "source": "augmented",
    "license": {
      "name": "Creative Commons Attribution 4.0 International",
      "url": "https://creativecommons.org/licenses/by/4.0/"
    }
  },
  "images": [
    {
      "id": 9130122639,
      "width": 256,
      "height": 256,
      "file_name": "image (902).JPG",
      "size": 10370,
      "format": "JPG",
      "url": "",
      "hash": "",
      "status": "success"
    }
  ],
  "annotations": [
    {
      "id": 9683600641,
      "image_id": 9130122639,
      "category_id": 1000000002,
      "segmentation": [],
      "area": 196,
      "bbox": [
        225,
        206,
        22,
        14
      ]
    },
    {
      "id": 6218512641,
      "image_id": 9130122639,
      "category_id": 1000000002,
      "segmentation": [],
      "area": 1129,
      "bbox": [
        148,
        133,
        60,
        71
      ]
    },
    {
      "id": 5757998641,
      "image_id": 9130122639,
      "category_id": 1000000002,
      "segmentation": [],
      "area": 149,
      "bbox": [
        107,
        185,
        21,
        14
      ]
    },
    {
      "id": 4405564641,
      "image_id": 9130122639,
      "category_id": 1000000002,
      "segmentation": [],
      "area": 153,
      "bbox": [
        63,
        145,
        34,
        37
      ]
    },
    {
      "id": 7986521641,
      "image_id": 9130122639,
      "category_id": 1000000002,
      "segmentation": [],
      "area": 146,
      "bbox": [
        160,
        134,
        14,
        14
      ]
    },
    {
      "id": 4995959641,
      "image_id": 9130122639,
      "category_id": 1000000002,
      "segmentation": [],
      "area": 3653,
      "bbox": [
        7,
        6,
        159,
        135
      ]
    },
    {
      "id": 1861000641,
      "image_id": 9130122639,
      "category_id": 1000000002,
      "segmentation": [],
      "area": 306,
      "bbox": [
        89,
        105,
        20,
        23
      ]
    },
    {
      "id": 5998969641,
      "image_id": 9130122639,
      "category_id": 1000000002,
      "segmentation": [],
      "area": 135,
      "bbox": [
        116,
        99,
        12,
        17
      ]
    },
    {
      "id": 4158076641,
      "image_id": 9130122639,
      "category_id": 1000000002,
      "segmentation": [],
      "area": 136,
      "bbox": [
        65,
        26,
        22,
        13
      ]
    }
  ],
  "categories": [
    {
      "id": 1000000002,
      "name": "Cedar_apple_rust",
      "supercategory": "Apple"
    }
  ]
}