{
  "info": {
    "description": "data",
    "version": "1.0",
    "year": 2025,
    "contributor": "search engine",
    "source": "augmented",
    "license": {
      "name": "Creative Commons Attribution 4.0 International",
      "url": "https://creativecommons.org/licenses/by/4.0/"
    }
  },
  "images": [
    {
      "id": 1424599131,
      "width": 256,
      "height": 256,
      "file_name": "image (110).JPG",
      "size": 9909,
      "format": "JPG",
      "url": "",
      "hash": "",
      "status": "success"
    }
  ],
  "annotations": [
    {
      "id": 2685733140,
      "image_id": 1424599131,
      "category_id": 1000000002,
      "segmentation": [],
      "area": 7330,
      "bbox": [
        15,
        15,
        197,
        241
      ]
    },
    {
      "id": 5583457140,
      "image_id": 1424599131,
      "category_id": 1000000002,
      "segmentation": [],
      "area": 134,
      "bbox": [
        171,
        203,
        16,
        12
      ]
    },
    {
      "id": 2557096140,
      "image_id": 1424599131,
      "category_id": 1000000002,
      "segmentation": [],
      "area": 375,
      "bbox": [
        159,
        177,
        39,
        23
      ]
    },
    {
      "id": 8622475140,
      "image_id": 1424599131,
      "category_id": 1000000002,
      "segmentation": [],
      "area": 103,
      "bbox": [
        145,
        176,
        9,
        15
      ]
    },
    {
      "id": 9779260140,
      "image_id": 1424599131,
      "category_id": 1000000002,
      "segmentation": [],
      "area": 313,
      "bbox": [
        134,
        144,
        24,
        25
      ]
    },
    {
      "id": 9626127140,
      "image_id": 1424599131,
      "category_id": 1000000002,
      "segmentation": [],
      "area": 122,
      "bbox": [
        103,
        144,
        14,
        11
      ]
    },
    {
      "id": 5299505140,
      "image_id": 1424599131,
      "category_id": 1000000002,
      "segmentation": [],
      "area": 326,
      "bbox": [
        140,
        100,
        36,
        23
      ]
    },
    {
      "id": 5809074140,
      "image_id": 1424599131,
      "category_id": 1000000002,
      "segmentation": [],
      "area": 299,
      "bbox": [
        42,
        92,
        22,
        21
      ]
    },
    {
      "id": 8478740140,
      "image_id": 1424599131,
      "category_id": 1000000002,
      "segmentation": [],
      "area": 278,
      "bbox": [
        143,
        78,
        23,
        16
      ]
    },
    {
      "id": 1127504140,
      "image_id": 1424599131,
      "category_id": 1000000002,
      "segmentation": [],
      "area": 151,
      "bbox": [
        166,
        53,
        42,
        39
      ]
    },
    {
      "id": 5584968140,
      "image_id": 1424599131,
      "category_id": 1000000002,
      "segmentation": [],
      "area": 207,
      "bbox": [
        105,
        63,
        22,
        14
      ]
    }
  ],
  "categories": [
    {
      "id": 1000000002,
      "name": "Cedar_apple_rust",
      "supercategory": "Apple"
    }
  ]
}