{
  "info": {
    "description": "data",
    "version": "1.0",
    "year": 2025,
    "contributor": "search engine",
    "source": "augmented",
    "license": {
      "name": "Creative Commons Attribution 4.0 International",
      "url": "https://creativecommons.org/licenses/by/4.0/"
    }
  },
  "images": [
    {
      "id": 2749039592,
      "width": 256,
      "height": 256,
      "file_name": "image (1208).JPG",
      "size": 15244,
      "format": "JPG",
      "url": "",
      "hash": "",
      "status": "success"
    }
  ],
  "annotations": [
    {
      "id": 6944412602,
      "image_id": 2749039592,
      "category_id": 1000000003,
      "segmentation": [],
      "area": 4393,
      "bbox": [
        91,
        58,
        140,
        180
      ]
    },
    {
      "id": 5857171602,
      "image_id": 2749039592,
      "category_id": 1000000003,
      "segmentation": [],
      "area": 215,
      "bbox": [
        92,
        154,
        27,
        42
      ]
    }
  ],
  "categories": [
    {
      "id": 1000000003,
      "name": "healthy",
      "supercategory": "Apple"
    }
  ]
}