{
  "info": {
    "description": "data",
    "version": "1.0",
    "year": 2025,
    "contributor": "search engine",
    "source": "augmented",
    "license": {
      "name": "Creative Commons Attribution 4.0 International",
      "url": "https://creativecommons.org/licenses/by/4.0/"
    }
  },
  "images": [
    {
      "id": 6282170039,
      "width": 256,
      "height": 256,
      "file_name": "image (1524).JPG",
      "size": 18702,
      "format": "JPG",
      "url": "",
      "hash": "",
      "status": "success"
    }
  ],
  "annotations": [
    {
      "id": 2092487052,
      "image_id": 6282170039,
      "category_id": 1000000003,
      "segmentation": [],
      "area": 851,
      "bbox": [
        149,
        37,
        44,
        78
      ]
    },
    {
      "id": 2154354052,
      "image_id": 6282170039,
      "category_id": 1000000003,
      "segmentation": [],
      "area": 352,
      "bbox": [
        112,
        52,
        32,
        62
      ]
    }
  ],
  "categories": [
    {
      "id": 1000000003,
      "name": "healthy",
      "supercategory": "Apple"
    }
  ]
}