{
  "info": {
    "description": "data",
    "version": "1.0",
    "year": 2025,
    "contributor": "search engine",
    "source": "no_augmentation",
    "license": {
      "name": "Creative Commons Attribution 4.0 International",
      "url": "https://creativecommons.org/licenses/by/4.0/"
    },
    "leaf_info": {
      "leaf_number": 495.0,
      "source": "plant_village_classification",
      "original_filename": "RS_HL 7384.JPG"
    }
  },
  "images": [
    {
      "id": 5150447877,
      "width": 256,
      "height": 256,
      "file_name": "image (1442).JPG",
      "size": 18947,
      "format": "JPG",
      "url": "",
      "hash": "",
      "status": "success",
      "original_filename": "RS_HL 7384.JPG",
      "pvc_filename": "dbe91ac0-dcec-40f0-8be3-be2cafd83d5a___RS_HL 7384.JPG"
    }
  ],
  "annotations": [
    {
      "id": 8492912887,
      "image_id": 5150447877,
      "category_id": 2000000003,
      "segmentation": [],
      "area": 116,
      "bbox": [
        147,
        216,
        18,
        14
      ]
    },
    {
      "id": 1263541887,
      "image_id": 5150447877,
      "category_id": 2000000003,
      "segmentation": [],
      "area": 245,
      "bbox": [
        102,
        204,
        42,
        24
      ]
    },
    {
      "id": 4243416887,
      "image_id": 5150447877,
      "category_id": 2000000003,
      "segmentation": [],
      "area": 2408,
      "bbox": [
        32,
        98,
        79,
        104
      ]
    },
    {
      "id": 2888200887,
      "image_id": 5150447877,
      "category_id": 2000000003,
      "segmentation": [],
      "area": 7084,
      "bbox": [
        41,
        0,
        193,
        127
      ]
    }
  ],
  "categories": [
    {
      "id": 2000000003,
      "name": "healthy",
      "supercategory": "Apple"
    }
  ]
}