{
  "info": {
    "description": "data",
    "version": "1.0",
    "year": 2025,
    "contributor": "search engine",
    "source": "augmented",
    "license": {
      "name": "Creative Commons Attribution 4.0 International",
      "url": "https://creativecommons.org/licenses/by/4.0/"
    }
  },
  "images": [
    {
      "id": 4357694564,
      "width": 256,
      "height": 256,
      "file_name": "image (421).JPG",
      "size": 20333,
      "format": "JPG",
      "url": "",
      "hash": "",
      "status": "success"
    }
  ],
  "annotations": [
    {
      "id": 9695282575,
      "image_id": 4357694564,
      "category_id": 1000000001,
      "segmentation": [],
      "area": 260,
      "bbox": [
        63,
        224,
        30,
        21
      ]
    },
    {
      "id": 8157178575,
      "image_id": 4357694564,
      "category_id": 1000000001,
      "segmentation": [],
      "area": 755,
      "bbox": [
        94,
        207,
        79,
        38
      ]
    },
    {
      "id": 3460640575,
      "image_id": 4357694564,
      "category_id": 1000000001,
      "segmentation": [],
      "area": 809,
      "bbox": [
        12,
        169,
        35,
        68
      ]
    },
    {
      "id": 4342247575,
      "image_id": 4357694564,
      "category_id": 1000000001,
      "segmentation": [],
      "area": 567,
      "bbox": [
        9,
        103,
        28,
        59
      ]
    },
    {
      "id": 4154677575,
      "image_id": 4357694564,
      "category_id": 1000000001,
      "segmentation": [],
      "area": 201,
      "bbox": [
        190,
        73,
        38,
        76
      ]
    },
    {
      "id": 3426656575,
      "image_id": 4357694564,
      "category_id": 1000000001,
      "segmentation": [],
      "area": 214,
      "bbox": [
        153,
        120,
        29,
        24
      ]
    },
    {
      "id": 3488322575,
      "image_id": 4357694564,
      "category_id": 1000000001,
      "segmentation": [],
      "area": 180,
      "bbox": [
        132,
        73,
        19,
        16
      ]
    },
    {
      "id": 3862540575,
      "image_id": 4357694564,
      "category_id": 1000000001,
      "segmentation": [],
      "area": 1097,
      "bbox": [
        137,
        0,
        113,
        79
      ]
    },
    {
      "id": 9191045575,
      "image_id": 4357694564,
      "category_id": 1000000001,
      "segmentation": [],
      "area": 132,
      "bbox": [
        47,
        48,
        36,
        23
      ]
    }
  ],
  "categories": [
    {
      "id": 1000000001,
      "name": "Black_rot",
      "supercategory": "Apple"
    }
  ]
}