{
  "info": {
    "description": "data",
    "version": "1.0",
    "year": 2025,
    "contributor": "search engine",
    "source": "augmented",
    "license": {
      "name": "Creative Commons Attribution 4.0 International",
      "url": "https://creativecommons.org/licenses/by/4.0/"
    }
  },
  "images": [
    {
      "id": 3125531559,
      "width": 256,
      "height": 256,
      "file_name": "image (264).JPG",
      "size": 18104,
      "format": "JPG",
      "url": "",
      "hash": "",
      "status": "success"
    }
  ],
  "annotations": [
    {
      "id": 1824446569,
      "image_id": 3125531559,
      "category_id": 1000000001,
      "segmentation": [],
      "area": 822,
      "bbox": [
        5,
        80,
        92,
        169
      ]
    },
    {
      "id": 9951940569,
      "image_id": 3125531559,
      "category_id": 1000000001,
      "segmentation": [],
      "area": 210,
      "bbox": [
        162,
        139,
        59,
        85
      ]
    },
    {
      "id": 8095891569,
      "image_id": 3125531559,
      "category_id": 1000000001,
      "segmentation": [],
      "area": 110,
      "bbox": [
        211,
        110,
        12,
        25
      ]
    },
    {
      "id": 3494651569,
      "image_id": 3125531559,
      "category_id": 1000000001,
      "segmentation": [],
      "area": 647,
      "bbox": [
        196,
        5,
        57,
        66
      ]
    }
  ],
  "categories": [
    {
      "id": 1000000001,
      "name": "Black_rot",
      "supercategory": "Apple"
    }
  ]
}