{
  "info": {
    "description": "data",
    "version": "1.0",
    "year": 2025,
    "contributor": "search engine",
    "source": "augmented",
    "license": {
      "name": "Creative Commons Attribution 4.0 International",
      "url": "https://creativecommons.org/licenses/by/4.0/"
    }
  },
  "images": [
    {
      "id": 5456563781,
      "width": 256,
      "height": 256,
      "file_name": "image (208).JPG",
      "size": 17435,
      "format": "JPG",
      "url": "",
      "hash": "",
      "status": "success"
    }
  ],
  "annotations": [
    {
      "id": 8891056790,
      "image_id": 5456563781,
      "category_id": 1000000000,
      "segmentation": [],
      "area": 710,
      "bbox": [
        145,
        169,
        60,
        61
      ]
    },
    {
      "id": 8577910790,
      "image_id": 5456563781,
      "category_id": 1000000000,
      "segmentation": [],
      "area": 272,
      "bbox": [
        60,
        169,
        25,
        36
      ]
    },
    {
      "id": 8059238790,
      "image_id": 5456563781,
      "category_id": 1000000000,
      "segmentation": [],
      "area": 141,
      "bbox": [
        64,
        155,
        18,
        16
      ]
    },
    {
      "id": 6132569790,
      "image_id": 5456563781,
      "category_id": 1000000000,
      "segmentation": [],
      "area": 270,
      "bbox": [
        125,
        128,
        16,
        36
      ]
    },
    {
      "id": 5840921790,
      "image_id": 5456563781,
      "category_id": 1000000000,
      "segmentation": [],
      "area": 173,
      "bbox": [
        56,
        138,
        13,
        21
      ]
    },
    {
      "id": 9811083790,
      "image_id": 5456563781,
      "category_id": 1000000000,
      "segmentation": [],
      "area": 108,
      "bbox": [
        104,
        140,
        20,
        17
      ]
    },
    {
      "id": 7316539790,
      "image_id": 5456563781,
      "category_id": 1000000000,
      "segmentation": [],
      "area": 188,
      "bbox": [
        75,
        119,
        20,
        15
      ]
    },
    {
      "id": 2134113790,
      "image_id": 5456563781,
      "category_id": 1000000000,
      "segmentation": [],
      "area": 127,
      "bbox": [
        130,
        106,
        10,
        19
      ]
    },
    {
      "id": 3610382790,
      "image_id": 5456563781,
      "category_id": 1000000000,
      "segmentation": [],
      "area": 138,
      "bbox": [
        102,
        100,
        15,
        16
      ]
    },
    {
      "id": 1465996790,
      "image_id": 5456563781,
      "category_id": 1000000000,
      "segmentation": [],
      "area": 450,
      "bbox": [
        123,
        0,
        18,
        88
      ]
    },
    {
      "id": 5596393790,
      "image_id": 5456563781,
      "category_id": 1000000000,
      "segmentation": [],
      "area": 3711,
      "bbox": [
        0,
        0,
        97,
        64
      ]
    }
  ],
  "categories": [
    {
      "id": 1000000000,
      "name": "Apple_scab",
      "supercategory": "Apple"
    }
  ]
}