{
  "info": {
    "description": "data",
    "version": "1.0",
    "year": 2025,
    "contributor": "search engine",
    "source": "augmented",
    "license": {
      "name": "Creative Commons Attribution 4.0 International",
      "url": "https://creativecommons.org/licenses/by/4.0/"
    }
  },
  "images": [
    {
      "id": 7604477632,
      "width": 350,
      "height": 350,
      "file_name": "image (794).JPG",
      "size": 15429,
      "format": "JPG",
      "url": "",
      "hash": "",
      "status": "success"
    }
  ],
  "annotations": [
    {
      "id": 9973101641,
      "image_id": 7604477632,
      "category_id": 1000000000,
      "segmentation": [],
      "area": 7095,
      "bbox": [
        191,
        93,
        159,
        245
      ]
    },
    {
      "id": 3681101641,
      "image_id": 7604477632,
      "category_id": 1000000000,
      "segmentation": [],
      "area": 23545,
      "bbox": [
        0,
        79,
        243,
        255
      ]
    },
    {
      "id": 8572143641,
      "image_id": 7604477632,
      "category_id": 1000000000,
      "segmentation": [],
      "area": 2742,
      "bbox": [
        2,
        0,
        189,
        94
      ]
    }
  ],
  "categories": [
    {
      "id": 1000000000,
      "name": "Apple_scab",
      "supercategory": "Apple"
    }
  ]
}