{
  "info": {
    "description": "data",
    "version": "1.0",
    "year": 2025,
    "contributor": "search engine",
    "source": "augmented",
    "license": {
      "name": "Creative Commons Attribution 4.0 International",
      "url": "https://creativecommons.org/licenses/by/4.0/"
    }
  },
  "images": [
    {
      "id": 9299448867,
      "width": 350,
      "height": 350,
      "file_name": "image (736).JPG",
      "size": 14711,
      "format": "JPG",
      "url": "",
      "hash": "",
      "status": "success"
    }
  ],
  "annotations": [
    {
      "id": 6176913878,
      "image_id": 9299448867,
      "category_id": 1000000000,
      "segmentation": [],
      "area": 210,
      "bbox": [
        322,
        331,
        28,
        19
      ]
    },
    {
      "id": 9397247878,
      "image_id": 9299448867,
      "category_id": 1000000000,
      "segmentation": [],
      "area": 3365,
      "bbox": [
        248,
        223,
        80,
        100
      ]
    },
    {
      "id": 5664957878,
      "image_id": 9299448867,
      "category_id": 1000000000,
      "segmentation": [],
      "area": 120,
      "bbox": [
        342,
        302,
        8,
        20
      ]
    },
    {
      "id": 6550682878,
      "image_id": 9299448867,
      "category_id": 1000000000,
      "segmentation": [],
      "area": 1895,
      "bbox": [
        13,
        217,
        108,
        96
      ]
    },
    {
      "id": 2058139878,
      "image_id": 9299448867,
      "category_id": 1000000000,
      "segmentation": [],
      "area": 242,
      "bbox": [
        142,
        264,
        13,
        27
      ]
    },
    {
      "id": 2953035878,
      "image_id": 9299448867,
      "category_id": 1000000000,
      "segmentation": [],
      "area": 257,
      "bbox": [
        323,
        242,
        21,
        41
      ]
    },
    {
      "id": 7404272878,
      "image_id": 9299448867,
      "category_id": 1000000000,
      "segmentation": [],
      "area": 653,
      "bbox": [
        328,
        169,
        22,
        98
      ]
    },
    {
      "id": 2264296878,
      "image_id": 9299448867,
      "category_id": 1000000000,
      "segmentation": [],
      "area": 4866,
      "bbox": [
        182,
        116,
        71,
        145
      ]
    },
    {
      "id": 9177430878,
      "image_id": 9299448867,
      "category_id": 1000000000,
      "segmentation": [],
      "area": 261,
      "bbox": [
        4,
        167,
        35,
        14
      ]
    },
    {
      "id": 9925123878,
      "image_id": 9299448867,
      "category_id": 1000000000,
      "segmentation": [],
      "area": 184,
      "bbox": [
        132,
        157,
        19,
        17
      ]
    },
    {
      "id": 7241593878,
      "image_id": 9299448867,
      "category_id": 1000000000,
      "segmentation": [],
      "area": 216,
      "bbox": [
        69,
        157,
        43,
        13
      ]
    },
    {
      "id": 9477336878,
      "image_id": 9299448867,
      "category_id": 1000000000,
      "segmentation": [],
      "area": 3270,
      "bbox": [
        256,
        61,
        56,
        105
      ]
    },
    {
      "id": 5578403878,
      "image_id": 9299448867,
      "category_id": 1000000000,
      "segmentation": [],
      "area": 1240,
      "bbox": [
        100,
        41,
        40,
        54
      ]
    },
    {
      "id": 1853363878,
      "image_id": 9299448867,
      "category_id": 1000000000,
      "segmentation": [],
      "area": 771,
      "bbox": [
        167,
        6,
        43,
        44
      ]
    }
  ],
  "categories": [
    {
      "id": 1000000000,
      "name": "Apple_scab",
      "supercategory": "Apple"
    }
  ]
}